mlos/__init__.py
mlos/apihandler.py
mlos/deployedmodel.py
mlos/invprocess.py
mlos/mloslogs.py
mlos/modeling.py
mlos/module_1.py
mlos/module_2.py
mlos/module_3.py
mlos/module_4.py
mlos/module_5.py
mlos/module_6.py
mlos/varstore.py
mlos-0.2.5.dist-info/METADATA
mlos-0.2.5.dist-info/WHEEL
mlos-0.2.5.dist-info/top_level.txt
mlos-0.2.5.dist-info/RECORD
